bedrock_protocol/nbt/__init__.py
bedrock_protocol_nbt-2.0.0.dist-info/licenses/LICENSE
tests/test.py
bedrock_protocol_nbt-2.0.0.dist-info/METADATA
bedrock_protocol_nbt-2.0.0.dist-info/WHEEL
bedrock_protocol_nbt-2.0.0.dist-info/top_level.txt
bedrock_protocol_nbt-2.0.0.dist-info/RECORD
