Metadata-Version: 2.4
Name: bedrock-protocol-nbt
Version: 2.0.0
Summary: Minecraft NBT Library
Author: GlacieTeam
License: MPL-2.0
Project-URL: homepage, https://github.com/GlacieTeam/bedrock-protocol-nbt
Classifier: Programming Language :: Python :: 3
Classifier: License :: OSI Approved :: Mozilla Public License 2.0 (MPL 2.0)
Classifier: Operating System :: OS Independent
Requires-Python: >=3
License-File: LICENSE
Requires-Dist: rapidnbt>=1.1.5
Dynamic: license-file
